MANIFEST.in
README_PUBLIC.md
setup.cfg
setup.py
iterable_etl/__init__.py
iterable_etl/__main__.py
iterable_etl/iterable_etl.py
iterable_etl.egg-info/PKG-INFO
iterable_etl.egg-info/SOURCES.txt
iterable_etl.egg-info/dependency_links.txt
iterable_etl.egg-info/requires.txt
iterable_etl.egg-info/top_level.txt
iterable_etl/libs/__init__.py
iterable_etl/libs/cnst.py
iterable_etl/libs/dbg.py
iterable_etl/libs/network.py
iterable_etl/libs/spark.py
iterable_etl/libs/transform.py
iterable_etl/tables/__init__.py
iterable_etl/tables/campaign_history.py
iterable_etl/tables/campaign_list_history.py
iterable_etl/tables/campaign_metrics.py
iterable_etl/tables/list.py
iterable_etl/tables/list_user_history.py
iterable_etl/tables/user_history.py
tests/__init__.py