Metadata-Version: 2.1
Name: iterable-etl
Version: 0.2.1
Summary: Replicate iterable data in databricks
Home-page: https://github.com/neofinancial/iterable_etl
Author: Neo Financial
Author-email: engineering@neofinancial.com
License: UNLICENSED
Platform: UNKNOWN
Classifier: Development Status :: 2 - Pre-Alpha
Classifier: Intended Audience :: Developers
Classifier: Natural Language :: English
Classifier: Programming Language :: Python :: 3
Requires-Python: >=3.6
